LICENSE
README.md
setup.py
ai_metadata/__init__.py
ai_metadata/base.py
ai_metadata/custom.py
ai_metadata/keras.py
ai_metadata/lightgbm.py
ai_metadata/onnx.py
ai_metadata/pmml.py
ai_metadata/pytorch.py
ai_metadata/sklearn.py
ai_metadata/spark.py
ai_metadata/utils.py
ai_metadata/version.py
ai_metadata/xgboost.py
ai_metadata.egg-info/PKG-INFO
ai_metadata.egg-info/SOURCES.txt
ai_metadata.egg-info/dependency_links.txt
ai_metadata.egg-info/requires.txt
ai_metadata.egg-info/top_level.txt
test/test_keras.py
test/test_lightgbm.py
test/test_onnx.py
test/test_pmml.py
test/test_pytorch.py
test/test_sklearn.py
test/test_spark.py
test/test_xgboost.py