Metadata-Version: 2.1
Name: ai-metadata
Version: 1.0.0
Summary: Detect and extract metadata about AI/ML models for deployment and visualization
Home-page: https://github.com/autodeployai/ai-metadata
Download-URL: https://github.com/autodeployai/ai-metadata/archive/v1.0.0.tar.gz
Author: AutoDeployAI
Author-email: autodeploy.ai@gmail.com
License: Apache License 2.0
Classifier: Development Status :: 4 - Beta
Classifier: Environment :: Console
Classifier: Environment :: Web Environment
Classifier: Intended Audience :: Developers
Classifier: Intended Audience :: System Administrators
Classifier: License :: OSI Approved :: Apache Software License
Classifier: Operating System :: OS Independent
Classifier: Programming Language :: Python :: 2.7
Classifier: Programming Language :: Python :: 3.5
Classifier: Programming Language :: Python :: 3.6
Classifier: Programming Language :: Python :: 3.7
Classifier: Programming Language :: Python :: 3.8
Classifier: Programming Language :: Python :: 3.9
Classifier: Programming Language :: Python :: 3.10
Classifier: Topic :: Scientific/Engineering :: Artificial Intelligence
License-File: LICENSE
